riskcloudpy/__init__.py
riskcloudpy/session.py
riskcloudpy-0.1.1.dist-info/METADATA
riskcloudpy-0.1.1.dist-info/WHEEL
riskcloudpy-0.1.1.dist-info/top_level.txt
riskcloudpy-0.1.1.dist-info/RECORD
