Metadata-Version: 2.1
Name: riskcloudpy
Version: 0.1.1
Summary: A Python SDK for the Risk Cloud
Home-page: UNKNOWN
Author: LogicGate
License: MIT
Platform: UNKNOWN
Requires-Dist: requests
